setup.py
brynq_sdk_sage/__init__.py
brynq_sdk_sage/absences.py
brynq_sdk_sage/costcentres.py
brynq_sdk_sage/deductions.py
brynq_sdk_sage/departments.py
brynq_sdk_sage/employees.py
brynq_sdk_sage/payments.py
brynq_sdk_sage.egg-info/PKG-INFO
brynq_sdk_sage.egg-info/SOURCES.txt
brynq_sdk_sage.egg-info/dependency_links.txt
brynq_sdk_sage.egg-info/not-zip-safe
brynq_sdk_sage.egg-info/requires.txt
brynq_sdk_sage.egg-info/top_level.txt