Metadata-Version: 1.0
Name: brynq-sdk-sage
Version: 1.0.2
Summary: Sage 50 UK on premise wrapper from BrynQ
Home-page: UNKNOWN
Author: BrynQ
Author-email: support@brynq.com
License: BrynQ License
Platform: UNKNOWN
